qpvdi/__init__.py
qpvdi/injector.py
qpvdi-0.0.6.dist-info/LICENSE
qpvdi-0.0.6.dist-info/METADATA
qpvdi-0.0.6.dist-info/WHEEL
qpvdi-0.0.6.dist-info/top_level.txt
qpvdi-0.0.6.dist-info/RECORD
