Metadata-Version: 2.1
Name: qpvdi
Version: 0.0.6
Summary: Dependency injection
Home-page: https://github.com/quangpv/python-dependency-injection
Author: Quangpv
Author-email: quangpv.uit@gmail.com
License: UNKNOWN
Project-URL: Bug Tracker, https://github.com/quangpv/python-dependency-injection/issues
Platform: UNKNOWN
Classifier: Programming Language :: Python :: 3
Classifier: License :: OSI Approved :: MIT License
Classifier: Operating System :: OS Independent
Requires-Python: >=3.6
License-File: LICENSE
